game_utilities.py
ruben_curses_game_utilities-0.2.0.dist-info/LICENSE
ruben_curses_game_utilities-0.2.0.dist-info/METADATA
ruben_curses_game_utilities-0.2.0.dist-info/WHEEL
ruben_curses_game_utilities-0.2.0.dist-info/top_level.txt
ruben_curses_game_utilities-0.2.0.dist-info/RECORD
